ped_parser/__init__.py
ped_parser/exceptions.py
ped_parser/family.py
ped_parser/individual.py
ped_parser/log.py
ped_parser/parser.py
ped_parser-1.6.6.data/scripts/ped_parser
ped_parser-1.6.6.dist-info/DESCRIPTION.rst
ped_parser-1.6.6.dist-info/METADATA
ped_parser-1.6.6.dist-info/RECORD
ped_parser-1.6.6.dist-info/WHEEL
ped_parser-1.6.6.dist-info/metadata.json
ped_parser-1.6.6.dist-info/top_level.txt
